strip_hints/__init__.py
strip_hints/import_hooks.py
strip_hints/import_hooks_py3.py
strip_hints/strip_hints_main.py
strip_hints/token_list.py
strip_hints-0.1.12.dist-info/LICENSE.txt
strip_hints-0.1.12.dist-info/METADATA
strip_hints-0.1.12.dist-info/WHEEL
strip_hints-0.1.12.dist-info/entry_points.txt
strip_hints-0.1.12.dist-info/top_level.txt
strip_hints-0.1.12.dist-info/RECORD
