Metadata-Version: 2.2
Name: strip-hints
Version: 0.1.12
Summary: Function and command-line program to strip Python type hints.
Author-email: Allen Barker <Allen.L.Barker@gmail.com>
License: The MIT License (MIT)
Project-URL: Homepage, https://github.com/abarker/strip-hints
Keywords: annotations,hints,strip,type,typing
Classifier: Development Status :: 4 - Beta
Classifier: Intended Audience :: Developers
Classifier: Operating System :: Microsoft :: Windows
Classifier: Operating System :: POSIX
Classifier: Operating System :: Unix
Classifier: Programming Language :: Python
Classifier: Programming Language :: Python :: 2.7
Classifier: Programming Language :: Python :: 3
Classifier: Programming Language :: Python :: 3.3
Classifier: Programming Language :: Python :: 3.4
Classifier: Programming Language :: Python :: 3.5
Classifier: Programming Language :: Python :: Implementation :: CPython
Classifier: Programming Language :: Python :: Implementation :: PyPy
Classifier: Topic :: Utilities
License-File: LICENSE.txt
Requires-Dist: wheel
